google_pubsub_adapter/__init__.py
google_pubsub_adapter/apps.py
google_pubsub_adapter/constants.py
google_pubsub_adapter/management/__init__.py
google_pubsub_adapter/management/commands/__init__.py
google_pubsub_adapter/management/commands/init_pubsub.py
google_pubsub_adapter/publisher/__init__.py
google_pubsub_adapter/publisher/google_pubsub_publisher.py
tests/__init__.py
tests/conftest.py
tests/google_pubsub_adapter/__init__.py
tests/google_pubsub_adapter/test_app_loading.py
tests/google_pubsub_adapter/publisher/__init__.py
tests/google_pubsub_adapter/publisher/test_google_pubsub_publisher.py
herbie_google_pubsub_adapter-1.0b1.dist-info/LICENSE
herbie_google_pubsub_adapter-1.0b1.dist-info/METADATA
herbie_google_pubsub_adapter-1.0b1.dist-info/WHEEL
herbie_google_pubsub_adapter-1.0b1.dist-info/top_level.txt
herbie_google_pubsub_adapter-1.0b1.dist-info/RECORD
